spacetrackapi/__init__.py
spacetrackapi/client.py
spacetrackapi/exceptions.py
spacetrackapi/throttler.py
spacetrackapi/urlbuilder.py
spacetrackapi-0.1.1.dist-info/DESCRIPTION.rst
spacetrackapi-0.1.1.dist-info/METADATA
spacetrackapi-0.1.1.dist-info/RECORD
spacetrackapi-0.1.1.dist-info/WHEEL
spacetrackapi-0.1.1.dist-info/metadata.json
spacetrackapi-0.1.1.dist-info/top_level.txt
