Metadata-Version: 2.0
Name: spacetrackapi
Version: 0.1.1
Summary: A client for the Space-Track API
Home-page: https://github.com/didieralber/Python-SpaceTrackAPI
Author: Didier Alber
Author-email: didier.alber@gmail.com
License: MIT
Keywords: spacetrack Space-Track
Platform: UNKNOWN
Classifier: Development Status :: 3 - Alpha
Classifier: Intended Audience :: Developers
Classifier: Topic :: Software Development :: Build Tools
Classifier: License :: OSI Approved :: MIT License
Classifier: Programming Language :: Python :: 3
Classifier: Programming Language :: Python :: 3.5
Requires-Dist: requests (==2.9.1)
